README.rst
mtc.py
setup.py
mintty_colors.egg-info/PKG-INFO
mintty_colors.egg-info/SOURCES.txt
mintty_colors.egg-info/dependency_links.txt
mintty_colors.egg-info/entry_points.txt
mintty_colors.egg-info/requires.txt
mintty_colors.egg-info/top_level.txt