Metadata-Version: 1.0
Name: mintty-colors
Version: 1.0.0
Summary: Switch color themes on the fly in cygwin's mintty terminal
Home-page: https://github.com/joakimkarlsson/mintty-colors
Author: Joakim Karlsson
Author-email: joakim@jkarlsson.com
License: MIT
Keywords: cyginw mintty colors
Platform: UNKNOWN
